Workbook

Sheet Bill Ledger
A1: Grand Lakes MUD 2 - Account 30402-0600812002 - 3923 Rose Grove Ln, Katy TX
A2: Every bill transcribed from the scanned images. Blue = read off the bill. Black = calculated by formula.
A4: Service End | B4: Year | C4: Month | D4: Meter Prev | E4: Meter Pres | F4: kGal Used | G4: Water $ | H4: Sewer $ | I4: NFBWA Rate | J4: NFBWA $ | K4: SPA Credit $ | L4: Other $ | M4: Bill Total $ | N4: Check: Sum | O4: Delta | P4: $ per kGal | Q4: Fixed $ | R4: Variable $
A5: 2021-08-13 | B5: 2021 | C5: 8 | D5: 747 | E5: 750 | F5: 3 | G5: 1.5 | H5: 3.33 | I5: 4.5 | J5: 13.5 | K5: 0 | L5: 180 | M5: 198.33 | N5: =G5+H5+J5+K5+L5 -> 198.33 | O5: =ROUND(N5-M5,2) -> 0 | P5: =IF(F5=0,"",M5/F5) -> 66.11 | Q5: =IF(A5<"2024-02",H5,25+H5) -> 3.33 | R5: =M5-Q5 -> 195
A6: 2021-09-13 | B6: 2021 | C6: 9 | D6: 750 | E6: 764 | F6: 14 | G6: 7 | H6: 10 | I6: 4.5 | J6: 63 | K6: 0 | L6: 0 | M6: 80 | N6: =G6+H6+J6+K6+L6 -> 80 | O6: =ROUND(N6-M6,2) -> 0 | P6: =IF(F6=0,"",M6/F6) -> 5.7142857 | Q6: =IF(A6<"2024-02",H6,25+H6) -> 10 | R6: =M6-Q6 -> 70
A7: 2021-10-13 | B7: 2021 | C7: 10 | D7: 764 | E7: 774 | F7: 10 | G7: 5 | H7: 10 | I7: 4.5 | J7: 45 | K7: 0 | L7: 0 | M7: 60 | N7: =G7+H7+J7+K7+L7 -> 60 | O7: =ROUND(N7-M7,2) -> 0 | P7: =IF(F7=0,"",M7/F7) -> 6 | Q7: =IF(A7<"2024-02",H7,25+H7) -> 10 | R7: =M7-Q7 -> 50
A8: 2021-11-13 | B8: 2021 | C8: 11 | D8: 774 | E8: 787 | F8: 13 | G8: 6.5 | H8: 10 | I8: 4.5 | J8: 58.5 | K8: 0 | L8: 0 | M8: 75 | N8: =G8+H8+J8+K8+L8 -> 75 | O8: =ROUND(N8-M8,2) -> 0 | P8: =IF(F8=0,"",M8/F8) -> 5.7692308 | Q8: =IF(A8<"2024-02",H8,25+H8) -> 10 | R8: =M8-Q8 -> 65
A9: 2021-12-13 | B9: 2021 | C9: 12 | D9: 787 | E9: 794 | F9: 7 | G9: 3.5 | H9: 10 | I9: 4.5 | J9: 31.5 | K9: 0 | L9: 0 | M9: 45 | N9: =G9+H9+J9+K9+L9 -> 45 | O9: =ROUND(N9-M9,2) -> 0 | P9: =IF(F9=0,"",M9/F9) -> 6.4285714 | Q9: =IF(A9<"2024-02",H9,25+H9) -> 10 | R9: =M9-Q9 -> 35
A10: 2022-01-13 | B10: 2022 | C10: 1 | D10: 794 | E10: 802 | F10: 8 | G10: 4 | H10: 10 | I10: 4.5 | J10: 36 | K10: 0 | L10: 0 | M10: 50 | N10: =G10+H10+J10+K10+L10 -> 50 | O10: =ROUND(N10-M10,2) -> 0 | P10: =IF(F10=0,"",M10/F10) -> 6.25 | Q10: =IF(A10<"2024-02",H10,25+H10) -> 10 | R10: =M10-Q10 -> 40
A11: 2022-02-13 | B11: 2022 | C11: 2 | D11: 802 | E11: 805 | F11: 3 | G11: 1.5 | H11: 10 | I11: 4.8 | J11: 14.4 | K11: -6 | L11: 0 | M11: 19.9 | N11: =G11+H11+J11+K11+L11 -> 19.9 | O11: =ROUND(N11-M11,2) -> 0 | P11: =IF(F11=0,"",M11/F11) -> 6.6333333 | Q11: =IF(A11<"2024-02",H11,25+H11) -> 10 | R11: =M11-Q11 -> 9.9
A12: 2022-03-13 | B12: 2022 | C12: 3 | D12: 805 | E12: 809 | F12: 4 | G12: 2 | H12: 10 | I12: 4.8 | J12: 19.2 | K12: -8 | L12: 0 | M12: 23.2 | N12: =G12+H12+J12+K12+L12 -> 23.2 | O12: =ROUND(N12-M12,2) -> 0 | P12: =IF(F12=0,"",M12/F12) -> 5.8 | Q12: =IF(A12<"2024-02",H12,25+H12) -> 10 | R12: =M12-Q12 -> 13.2
A13: 2022-04-13 | B13: 2022 | C13: 4 | D13: 809 | E13: 816 | F13: 7 | G13: 3.5 | H13: 10 | I13: 4.8 | J13: 33.6 | K13: -14 | L13: 0 | M13: 33.1 | N13: =G13+H13+J13+K13+L13 -> 33.1 | O13: =ROUND(N13-M13,2) -> 0 | P13: =IF(F13=0,"",M13/F13) -> 4.7285714 | Q13: =IF(A13<"2024-02",H13,25+H13) -> 10 | R13: =M13-Q13 -> 23.1
A14: 2022-05-13 | B14: 2022 | C14: 5 | D14: 816 | E14: 827 | F14: 11 | G14: 5.5 | H14: 10 | I14: 4.8 | J14: 52.8 | K14: -22 | L14: 0 | M14: 46.3 | N14: =G14+H14+J14+K14+L14 -> 46.3 | O14: =ROUND(N14-M14,2) -> 0 | P14: =IF(F14=0,"",M14/F14) -> 4.2090909 | Q14: =IF(A14<"2024-02",H14,25+H14) -> 10 | R14: =M14-Q14 -> 36.3
A15: 2022-06-13 | B15: 2022 | C15: 6 | D15: 827 | E15: 843 | F15: 16 | G15: 8 | H15: 10 | I15: 4.8 | J15: 76.8 | K15: -32 | L15: 0 | M15: 62.8 | N15: =G15+H15+J15+K15+L15 -> 62.8 | O15: =ROUND(N15-M15,2) -> 0 | P15: =IF(F15=0,"",M15/F15) -> 3.925 | Q15: =IF(A15<"2024-02",H15,25+H15) -> 10 | R15: =M15-Q15 -> 52.8
A16: 2022-07-13 | B16: 2022 | C16: 7 | D16: 843 | E16: 861 | F16: 18 | G16: 9 | H16: 10 | I16: 4.9 | J16: 88.2 | K16: -36 | L16: 0 | M16: 71.2 | N16: =G16+H16+J16+K16+L16 -> 71.2 | O16: =ROUND(N16-M16,2) -> 0 | P16: =IF(F16=0,"",M16/F16) -> 3.9555556 | Q16: =IF(A16<"2024-02",H16,25+H16) -> 10 | R16: =M16-Q16 -> 61.2
... A64: 2026-07-13 | B64: 2026 | C64: 7 | D64: 1363 | E64: 1387 | F64: 24 | G64: 43 | H64: 20 | I64: 4.9 | J64: 117.6 | K64: 0 | L64: 0 | M64: 180.6 | N64: =G64+H64+J64+K64+L64 -> 180.6 | O64: =ROUND(N64-M64,2) -> 0 | P64: =IF(F64=0,"",M64/F64) -> 7.525 | Q64: =IF(A64<"2024-02",H64,25+H64) -> 45 | R64: =M64-Q64 -> 135.6
A65: TOTAL | F65: =SUM(F5:F64) -> 640 | G65: =SUM(G5:G64) -> 1004 | H65: =SUM(H5:H64) -> 893.33 | J65: =SUM(J5:J64) -> 3109.9 | K65: =SUM(K5:K64) -> -454 | L65: =SUM(L5:L64) -> 180 | M65: =SUM(M5:M64) -> 4733.23 | P65: =M65/F65 -> 7.3956719
A67: NOTE: 2024-06-13 row is RECONSTRUCTED. That bill is missing from the scans. Meter reads on the adjacent bills (1055 -> 1064) prove 9,000 gallons,
A68: and the July 2024 balance-forward of $187.11 reconciles exactly as $89.10 (May, unpaid) + $89.10 (June) + $8.91 penalty. Request the original from MDS.
A70: "Delta" column must be $0.00 on every row. It is. All 60 bills are internally consistent - the district made no arithmetic errors.
A71: "Fixed $" = charges you pay regardless of a drop of water (sewer, plus the $25 water minimum from Feb 2024). "Variable $" = everything driven by gallons.
A73: The blue bars in "kGal Used" and the red bars in "Bill Total" are conditional data bars - scroll down the column and the 2026 breakout is visible without a chart.

Sheet Annual Summary
A1: Annual Summary
A3: Year | B3: Bills | C3: kGal Used | D3: Total Paid | E3: $ / kGal | F3: vs Prior Yr Gallons | G3: vs Prior Yr Cost | H3: Min Month kGal | I3: Median kGal | J3: Max Month kGal
A4: 2021 | B4: =COUNTIF('Bill Ledger'!$B$5:$B$64,A4) -> 5 | C4: =SUMIF('Bill Ledger'!$B$5:$B$64,A4,'Bill Ledger'!$F$5:$F$64) -> 47 | D4: =SUMIF('Bill Ledger'!$B$5:$B$64,A4,'Bill Ledger'!$M$5:$M$64) -> 458.33 | E4: =D4/C4 -> 9.7517021 | H4: =MIN('Bill Ledger'!$F$5:$F$9) -> 3 | I4: =MEDIAN('Bill Ledger'!$F$5:$F$9) -> 10 | J4: =MAX('Bill Ledger'!$F$5:$F$9) -> 14
A5: 2022 | B5: =COUNTIF('Bill Ledger'!$B$5:$B$64,A5) -> 12 | C5: =SUMIF('Bill Ledger'!$B$5:$B$64,A5,'Bill Ledger'!$F$5:$F$64) -> 111 | D5: =SUMIF('Bill Ledger'!$B$5:$B$64,A5,'Bill Ledger'!$M$5:$M$64) -> 506.1 | E5: =D5/C5 -> 4.5594595 | F5: =C5/C4-1 -> 1.3617021 | G5: =D5/D4-1 -> 0.10422621 | H5: =MIN('Bill Ledger'!$F$10:$F$21) -> 3 | I5: =MEDIAN('Bill Ledger'!$F$10:$F$21) -> 7.5 | J5: =MAX('Bill Ledger'!$F$10:$F$21) -> 18
A6: 2023 | B6: =COUNTIF('Bill Ledger'!$B$5:$B$64,A6) -> 12 | C6: =SUMIF('Bill Ledger'!$B$5:$B$64,A6,'Bill Ledger'!$F$5:$F$64) -> 117 | D6: =SUMIF('Bill Ledger'!$B$5:$B$64,A6,'Bill Ledger'!$M$5:$M$64) -> 518.8 | E6: =D6/C6 -> 4.434188 | F6: =C6/C5-1 -> 0.054054054 | G6: =D6/D5-1 -> 0.025093855 | H6: =MIN('Bill Ledger'!$F$22:$F$33) -> 2 | I6: =MEDIAN('Bill Ledger'!$F$22:$F$33) -> 8 | J6: =MAX('Bill Ledger'!$F$22:$F$33) -> 21
A7: 2024 | B7: =COUNTIF('Bill Ledger'!$B$5:$B$64,A7) -> 12 | C7: =SUMIF('Bill Ledger'!$B$5:$B$64,A7,'Bill Ledger'!$F$5:$F$64) -> 109 | D7: =SUMIF('Bill Ledger'!$B$5:$B$64,A7,'Bill Ledger'!$M$5:$M$64) -> 1041.6 | E7: =D7/C7 -> 9.5559633 | F7: =C7/C6-1 -> -0.068376068 | G7: =D7/D6-1 -> 1.0077101 | H7: =MIN('Bill Ledger'!$F$34:$F$45) -> 3 | I7: =MEDIAN('Bill Ledger'!$F$34:$F$45) -> 9 | J7: =MAX('Bill Ledger'!$F$34:$F$45) -> 15
A8: 2025 | B8: =COUNTIF('Bill Ledger'!$B$5:$B$64,A8) -> 12 | C8: =SUMIF('Bill Ledger'!$B$5:$B$64,A8,'Bill Ledger'!$F$5:$F$64) -> 122 | D8: =SUMIF('Bill Ledger'!$B$5:$B$64,A8,'Bill Ledger'!$M$5:$M$64) -> 1159.8 | E8: =D8/C8 -> 9.5065574 | F8: =C8/C7-1 -> 0.11926606 | G8: =D8/D7-1 -> 0.11347926 | H8: =MIN('Bill Ledger'!$F$46:$F$57) -> 3 | I8: =MEDIAN('Bill Ledger'!$F$46:$F$57) -> 10.5 | J8: =MAX('Bill Ledger'!$F$46:$F$57) -> 18
A9: 2026 | B9: =COUNTIF('Bill Ledger'!$B$5:$B$64,A9) -> 7 | C9: =SUMIF('Bill Ledger'!$B$5:$B$64,A9,'Bill Ledger'!$F$5:$F$64) -> 134 | D9: =SUMIF('Bill Ledger'!$B$5:$B$64,A9,'Bill Ledger'!$M$5:$M$64) -> 1048.6 | E9: =D9/C9 -> 7.8253731 | F9: =C9/C8-1 -> 0.098360656 | G9: =D9/D8-1 -> -0.0958786 | H9: =MIN('Bill Ledger'!$F$58:$F$64) -> 11 | I9: =MEDIAN('Bill Ledger'!$F$58:$F$64) -> 22 | J9: =MAX('Bill Ledger'!$F$58:$F$64) -> 25
A11: 2021 = 5 bills (service started Aug 2021, includes $150 deposit + $30 transfer fee). 2026 = 7 bills (Jan-Jul, year in progress).
A13: Apples-to-apples: January through July only
A14: Year | B14: kGal Jan-Jul | C14: Paid Jan-Jul | D14: Gallons vs 2025 | E14: Cost vs 2025
A15: 2022 | B15: =SUMIFS('Bill Ledger'!$F$5:$F$64,'Bill Ledger'!$B$5:$B$64,A15,'Bill Ledger'!$C$5:$C$64,"<=7") -> 67 | C15: =SUMIFS('Bill Ledger'!$M$5:$M$64,'Bill Ledger'!$B$5:$B$64,A15,'Bill Ledger'!$C$5:$C$64,"<=7") -> 306.5 | D15: =B15/$B$18-1 -> 0.098360656 | E15: =C15/$C$18-1 -> -0.50715549
A16: 2023 | B16: =SUMIFS('Bill Ledger'!$F$5:$F$64,'Bill Ledger'!$B$5:$B$64,A16,'Bill Ledger'!$C$5:$C$64,"<=7") -> 56 | C16: =SUMIFS('Bill Ledger'!$M$5:$M$64,'Bill Ledger'!$B$5:$B$64,A16,'Bill Ledger'!$C$5:$C$64,"<=7") -> 260.4 | D16: =B16/$B$18-1 -> -0.081967213 | E16: =C16/$C$18-1 -> -0.58128316
A17: 2024 | B17: =SUMIFS('Bill Ledger'!$F$5:$F$64,'Bill Ledger'!$B$5:$B$64,A17,'Bill Ledger'!$C$5:$C$64,"<=7") -> 55 | C17: =SUMIFS('Bill Ledger'!$M$5:$M$64,'Bill Ledger'!$B$5:$B$64,A17,'Bill Ledger'!$C$5:$C$64,"<=7") -> 542 | D17: =B17/$B$18-1 -> -0.098360656 | E17: =C17/$C$18-1 -> -0.12847725
A18: 2025 | B18: =SUMIFS('Bill Ledger'!$F$5:$F$64,'Bill Ledger'!$B$5:$B$64,A18,'Bill Ledger'!$C$5:$C$64,"<=7") -> 61 | C18: =SUMIFS('Bill Ledger'!$M$5:$M$64,'Bill Ledger'!$B$5:$B$64,A18,'Bill Ledger'!$C$5:$C$64,"<=7") -> 621.9 | D18: =B18/$B$18-1 -> 0 | E18: =C18/$C$18-1 -> 0
A19: 2026 | B19: =SUMIFS('Bill Ledger'!$F$5:$F$64,'Bill Ledger'!$B$5:$B$64,A19,'Bill Ledger'!$C$5:$C$64,"<=7") -> 134 | C19: =SUMIFS('Bill Ledger'!$M$5:$M$64,'Bill Ledger'!$B$5:$B$64,A19,'Bill Ledger'!$C$5:$C$64,"<=7") -> 1048.6 | D19: =B19/$B$18-1 -> 1.1967213 | E19: =C19/$C$18-1 -> 0.68612317
A21: Rates were IDENTICAL in 2025 and 2026 (water $25 min / $1 / $2 tiers, sewer $20, NFBWA $4.90). So 100% of the 2026 increase is volume, not price.
A24: Winter usage (Jan+Feb+Mar) - the leak test
A25: Winter is indoor-only: no irrigation, no pool top-off, no car washing. It is the cleanest read on baseline household demand.
A26: Year | B26: Jan kGal | C26: Feb kGal | D26: Mar kGal | E26: Winter Total | F26: vs 4-Yr Avg
A27: 2022 | B27: =SUMIFS('Bill Ledger'!$F$5:$F$64,'Bill Ledger'!$B$5:$B$64,$A27,'Bill Ledger'!$C$5:$C$64,1) -> 8 | C27: =SUMIFS('Bill Ledger'!$F$5:$F$64,'Bill Ledger'!$B$5:$B$64,$A27,'Bill Ledger'!$C$5:$C$64,2) -> 3 | D27: =SUMIFS('Bill Ledger'!$F$5:$F$64,'Bill Ledger'!$B$5:$B$64,$A27,'Bill Ledger'!$C$5:$C$64,3) -> 4 | E27: =SUM(B27:D27) -> 15 | F27: =E27/AVERAGE($E$27:$E$30)-1 -> -0.076923077
A28: 2023 | B28: =SUMIFS('Bill Ledger'!$F$5:$F$64,'Bill Ledger'!$B$5:$B$64,$A28,'Bill Ledger'!$C$5:$C$64,1) -> 6 | C28: =SUMIFS('Bill Ledger'!$F$5:$F$64,'Bill Ledger'!$B$5:$B$64,$A28,'Bill Ledger'!$C$5:$C$64,2) -> 2 | D28: =SUMIFS('Bill Ledger'!$F$5:$F$64,'Bill Ledger'!$B$5:$B$64,$A28,'Bill Ledger'!$C$5:$C$64,3) -> 8 | E28: =SUM(B28:D28) -> 16 | F28: =E28/AVERAGE($E$27:$E$30)-1 -> -0.015384615
A29: 2024 | B29: =SUMIFS('Bill Ledger'!$F$5:$F$64,'Bill Ledger'!$B$5:$B$64,$A29,'Bill Ledger'!$C$5:$C$64,1) -> 7 | C29: =SUMIFS('Bill Ledger'!$F$5:$F$64,'Bill Ledger'!$B$5:$B$64,$A29,'Bill Ledger'!$C$5:$C$64,2) -> 3 | D29: =SUMIFS('Bill Ledger'!$F$5:$F$64,'Bill Ledger'!$B$5:$B$64,$A29,'Bill Ledger'!$C$5:$C$64,3) -> 8 | E29: =SUM(B29:D29) -> 18 | F29: =E29/AVERAGE($E$27:$E$30)-1 -> 0.10769231
A30: 2025 | B30: =SUMIFS('Bill Ledger'!$F$5:$F$64,'Bill Ledger'!$B$5:$B$64,$A30,'Bill Ledger'!$C$5:$C$64,1) -> 7 | C30: =SUMIFS('Bill Ledger'!$F$5:$F$64,'Bill Ledger'!$B$5:$B$64,$A30,'Bill Ledger'!$C$5:$C$64,2) -> 6 | D30: =SUMIFS('Bill Ledger'!$F$5:$F$64,'Bill Ledger'!$B$5:$B$64,$A30,'Bill Ledger'!$C$5:$C$64,3) -> 3 | E30: =SUM(B30:D30) -> 16 | F30: =E30/AVERAGE($E$27:$E$30)-1 -> -0.015384615
A31: 2026 | B31: =SUMIFS('Bill Ledger'!$F$5:$F$64,'Bill Ledger'!$B$5:$B$64,$A31,'Bill Ledger'!$C$5:$C$64,1) -> 15 | C31: =SUMIFS('Bill Ledger'!$F$5:$F$64,'Bill Ledger'!$B$5:$B$64,$A31,'Bill Ledger'!$C$5:$C$64,2) -> 11 | D31: =SUMIFS('Bill Ledger'!$F$5:$F$64,'Bill Ledger'!$B$5:$B$64,$A31,'Bill Ledger'!$C$5:$C$64,3) -> 15 | E31: =SUM(B31:D31) -> 41 | F31: =E31/AVERAGE($E$27:$E$30)-1 -> 1.5230769
A33: 2026 winter usage is 2.6x the 2022-2025 winter average. Nothing about a household changes in January. This is the single strongest piece of evidence.

Sheet Rate Model
A1: Reverse-Engineered Rate Schedule
A2: Derived by solving the printed line items against printed gallons across all 60 bills. The model reproduces every WATER charge to the cent, 60 of 60.
A4: Component | B4: Tier / Period | C4: Rate | D4: Note
B5: ERA 1: Aug 2021 - Jan 2024
A6: Water | B6: first 20,000 gal | C6: $0.50 per 1,000 gal | D6: no minimum charge
A7: Water | B7: above 20,000 gal | C7: $1.50 per 1,000 gal | D7: observed once, Aug 2023 (21 kGal = $11.50)
A8: Sewer | B8: flat | C8: $10.00 per month | D8: does not vary with usage
A9: NFBWA | B9: pass-through | C9: $4.50 -> $4.80 (Feb 2022) -> $4.90 (Jul 2022) | D9: North Fort Bend Water Authority, purely volumetric
A10: SPA Credit | B10: Feb 2022 - Jan 2024 | C10: -$2.00 per 1,000 gal | D10: district subsidy funded by the City of Houston agreement
B12: ERA 2: Feb 2024 - present
A13: Water | B13: first 10,000 gal | C13: $25.00 minimum | D13: you pay $25 even at zero gallons
A14: Water | B14: 10,000 - 20,000 gal | C14: $1.00 per 1,000 gal
A15: Water | B15: above 20,000 gal | C15: $2.00 per 1,000 gal | D15: first observed Apr 2026
A16: Sewer | B16: flat | C16: $20.00 per month | D16: doubled
A17: NFBWA | B17: pass-through | C17: $4.90 per 1,000 gal | D17: unchanged since Jul 2022 - four years
A18: SPA Credit | B18: removed | C18: $0.00 | D18: eliminated Feb 2024
A19: Penalty | B19: late | C19: 10% of the entire balance | D19: applied to the NFBWA pass-through too
A20: Delinquent Letter | B20: per occurrence | C20: $10.00 | D20: charged Jul 2024 and Mar 2025
A23: What the same month costs before and after the Feb 2024 restructure
A24: Monthly Usage (kGal) | B24: Era 1 Bill (2023 rates) | C24: Era 2 Bill (2024+ rates) | D24: Increase $ | E24: Increase %
A25: 0 | B25: =0.5*MIN(A25,20)+1.5*MAX(0,A25-20)+10+4.9*A25-2*A25 -> 10 | C25: =25+1*MAX(0,MIN(A25,20)-10)+2*MAX(0,A25-20)+20+4.9*A25 -> 45 | D25: =C25-B25 -> 35 | E25: =IF(B25=0,"n/a",C25/B25-1) -> 3.5
A26: 3 | B26: =0.5*MIN(A26,20)+1.5*MAX(0,A26-20)+10+4.9*A26-2*A26 -> 20.2 | C26: =25+1*MAX(0,MIN(A26,20)-10)+2*MAX(0,A26-20)+20+4.9*A26 -> 59.7 | D26: =C26-B26 -> 39.5 | E26: =IF(B26=0,"n/a",C26/B26-1) -> 1.9554455
A27: 5 | B27: =0.5*MIN(A27,20)+1.5*MAX(0,A27-20)+10+4.9*A27-2*A27 -> 27 | C27: =25+1*MAX(0,MIN(A27,20)-10)+2*MAX(0,A27-20)+20+4.9*A27 -> 69.5 | D27: =C27-B27 -> 42.5 | E27: =IF(B27=0,"n/a",C27/B27-1) -> 1.5740741
A28: 8 | B28: =0.5*MIN(A28,20)+1.5*MAX(0,A28-20)+10+4.9*A28-2*A28 -> 37.2 | C28: =25+1*MAX(0,MIN(A28,20)-10)+2*MAX(0,A28-20)+20+4.9*A28 -> 84.2 | D28: =C28-B28 -> 47 | E28: =IF(B28=0,"n/a",C28/B28-1) -> 1.2634409
A29: 10 | B29: =0.5*MIN(A29,20)+1.5*MAX(0,A29-20)+10+4.9*A29-2*A29 -> 44 | C29: =25+1*MAX(0,MIN(A29,20)-10)+2*MAX(0,A29-20)+20+4.9*A29 -> 94 | D29: =C29-B29 -> 50 | E29: =IF(B29=0,"n/a",C29/B29-1) -> 1.1363636
A30: 15 | B30: =0.5*MIN(A30,20)+1.5*MAX(0,A30-20)+10+4.9*A30-2*A30 -> 61 | C30: =25+1*MAX(0,MIN(A30,20)-10)+2*MAX(0,A30-20)+20+4.9*A30 -> 123.5 | D30: =C30-B30 -> 62.5 | E30: =IF(B30=0,"n/a",C30/B30-1) -> 1.0245902
A31: 20 | B31: =0.5*MIN(A31,20)+1.5*MAX(0,A31-20)+10+4.9*A31-2*A31 -> 78 | C31: =25+1*MAX(0,MIN(A31,20)-10)+2*MAX(0,A31-20)+20+4.9*A31 -> 153 | D31: =C31-B31 -> 75 | E31: =IF(B31=0,"n/a",C31/B31-1) -> 0.96153846
A32: 22 | B32: =0.5*MIN(A32,20)+1.5*MAX(0,A32-20)+10+4.9*A32-2*A32 -> 86.8 | C32: =25+1*MAX(0,MIN(A32,20)-10)+2*MAX(0,A32-20)+20+4.9*A32 -> 166.8 | D32: =C32-B32 -> 80 | E32: =IF(B32=0,"n/a",C32/B32-1) -> 0.92165899
A33: 25 | B33: =0.5*MIN(A33,20)+1.5*MAX(0,A33-20)+10+4.9*A33-2*A33 -> 100 | C33: =25+1*MAX(0,MIN(A33,20)-10)+2*MAX(0,A33-20)+20+4.9*A33 -> 187.5 | D33: =C33-B33 -> 87.5 | E33: =IF(B33=0,"n/a",C33/B33-1) -> 0.875
A35: The district's Feb 2024 letter said it would "increase water and sewer rates slightly." For a typical 8,000-gallon month the bill rose 126%.
A36: The fixed monthly floor - what you owe before using a single drop - went from $10.00 to $45.00. That is +350%, and it falls hardest on low-usage months.

Sheet Scenario Impact
A1: Proposed Rate Scenarios - Impact on This Household
A2: Source: EVO 10-Year Financial Operating Strategy handouts, GLMUD2 special meeting Aug 3, 2026. All totals INCLUDE the $4.90/1,000 NFBWA fee (the handout tables exclude it). Scenario 2 includes the $100/month Capital Project Base Fee.
A4: Monthly Usage (kGal) | B4: Current Total | C4: Scenario 1 Total | D4: Scenario 2 Total | E4: S1 vs Current | F4: S2 vs Current | G4: Note
A5: 3 | B5: =25+1*MAX(0,MIN(A5,20)-10)+2*MAX(0,MIN(A5,50)-20)+3*MAX(0,A5-50)+20+4.9*A5 -> 59.7 | C5: =30+1.5*MAX(0,MIN(A5,10)-5)+2*MAX(0,MIN(A5,15)-10)+2.5*MAX(0,MIN(A5,20)-15)+3*MAX(0,MIN(A5,25)-20)+3.5*MAX(0,MIN(A5,30)-25)+4*MAX(0,MIN(A5,35)-30)+4.5*MAX(0,MIN(A5,50)-35)+5*MAX(0,A5-50)+IF(A5<=20,55,IF(A5<=30,60,IF(A5<=40,65,IF(A5<=50,70,75))))+4.9*A5 -> 99.7 | D5: =30+3*MAX(0,MIN(A5,5)-2)+4*MAX(0,MIN(A5,9)-5)+4.5*MAX(0,MIN(A5,14)-9)+5.5*MAX(0,MIN(A5,20)-14)+6.5*MAX(0,MIN(A5,27)-20)+7.5*MAX(0,A5-27)+55+1.5*MAX(0,MIN(A5,8)-5)+2*MAX(0,MIN(A5,15)-8)+2.5*MAX(0,MIN(A5,20)-15)+3*MAX(0,MIN(A5,25)-20)+3.5*MAX(0,A5-25)+100+4.9*A5 -> 202.7 | E5: =C5/B5-1 -> 0.67001675 | F5: =D5/B5-1 -> 2.3953099
A6: 5 | B6: =25+1*MAX(0,MIN(A6,20)-10)+2*MAX(0,MIN(A6,50)-20)+3*MAX(0,A6-50)+20+4.9*A6 -> 69.5 | C6: =30+1.5*MAX(0,MIN(A6,10)-5)+2*MAX(0,MIN(A6,15)-10)+2.5*MAX(0,MIN(A6,20)-15)+3*MAX(0,MIN(A6,25)-20)+3.5*MAX(0,MIN(A6,30)-25)+4*MAX(0,MIN(A6,35)-30)+4.5*MAX(0,MIN(A6,50)-35)+5*MAX(0,A6-50)+IF(A6<=20,55,IF(A6<=30,60,IF(A6<=40,65,IF(A6<=50,70,75))))+4.9*A6 -> 109.5 | D6: =30+3*MAX(0,MIN(A6,5)-2)+4*MAX(0,MIN(A6,9)-5)+4.5*MAX(0,MIN(A6,14)-9)+5.5*MAX(0,MIN(A6,20)-14)+6.5*MAX(0,MIN(A6,27)-20)+7.5*MAX(0,A6-27)+55+1.5*MAX(0,MIN(A6,8)-5)+2*MAX(0,MIN(A6,15)-8)+2.5*MAX(0,MIN(A6,20)-15)+3*MAX(0,MIN(A6,25)-20)+3.5*MAX(0,A6-25)+100+4.9*A6 -> 218.5 | E6: =C6/B6-1 -> 0.57553957 | F6: =D6/B6-1 -> 2.1438849
A7: 7 | B7: =25+1*MAX(0,MIN(A7,20)-10)+2*MAX(0,MIN(A7,50)-20)+3*MAX(0,A7-50)+20+4.9*A7 -> 79.3 | C7: =30+1.5*MAX(0,MIN(A7,10)-5)+2*MAX(0,MIN(A7,15)-10)+2.5*MAX(0,MIN(A7,20)-15)+3*MAX(0,MIN(A7,25)-20)+3.5*MAX(0,MIN(A7,30)-25)+4*MAX(0,MIN(A7,35)-30)+4.5*MAX(0,MIN(A7,50)-35)+5*MAX(0,A7-50)+IF(A7<=20,55,IF(A7<=30,60,IF(A7<=40,65,IF(A7<=50,70,75))))+4.9*A7 -> 122.3 | D7: =30+3*MAX(0,MIN(A7,5)-2)+4*MAX(0,MIN(A7,9)-5)+4.5*MAX(0,MIN(A7,14)-9)+5.5*MAX(0,MIN(A7,20)-14)+6.5*MAX(0,MIN(A7,27)-20)+7.5*MAX(0,A7-27)+55+1.5*MAX(0,MIN(A7,8)-5)+2*MAX(0,MIN(A7,15)-8)+2.5*MAX(0,MIN(A7,20)-15)+3*MAX(0,MIN(A7,25)-20)+3.5*MAX(0,A7-25)+100+4.9*A7 -> 239.3 | E7: =C7/B7-1 -> 0.54224464 | F7: =D7/B7-1 -> 2.0176545 | G7: Neighbor at 3918 / your own low months
A8: 8 | B8: =25+1*MAX(0,MIN(A8,20)-10)+2*MAX(0,MIN(A8,50)-20)+3*MAX(0,A8-50)+20+4.9*A8 -> 84.2 | C8: =30+1.5*MAX(0,MIN(A8,10)-5)+2*MAX(0,MIN(A8,15)-10)+2.5*MAX(0,MIN(A8,20)-15)+3*MAX(0,MIN(A8,25)-20)+3.5*MAX(0,MIN(A8,30)-25)+4*MAX(0,MIN(A8,35)-30)+4.5*MAX(0,MIN(A8,50)-35)+5*MAX(0,A8-50)+IF(A8<=20,55,IF(A8<=30,60,IF(A8<=40,65,IF(A8<=50,70,75))))+4.9*A8 -> 128.7 | D8: =30+3*MAX(0,MIN(A8,5)-2)+4*MAX(0,MIN(A8,9)-5)+4.5*MAX(0,MIN(A8,14)-9)+5.5*MAX(0,MIN(A8,20)-14)+6.5*MAX(0,MIN(A8,27)-20)+7.5*MAX(0,A8-27)+55+1.5*MAX(0,MIN(A8,8)-5)+2*MAX(0,MIN(A8,15)-8)+2.5*MAX(0,MIN(A8,20)-15)+3*MAX(0,MIN(A8,25)-20)+3.5*MAX(0,A8-25)+100+4.9*A8 -> 249.7 | E8: =C8/B8-1 -> 0.52850356 | F8: =D8/B8-1 -> 1.9655582 | G8: Your 2021-2025 typical month
A9: 10 | B9: =25+1*MAX(0,MIN(A9,20)-10)+2*MAX(0,MIN(A9,50)-20)+3*MAX(0,A9-50)+20+4.9*A9 -> 94 | C9: =30+1.5*MAX(0,MIN(A9,10)-5)+2*MAX(0,MIN(A9,15)-10)+2.5*MAX(0,MIN(A9,20)-15)+3*MAX(0,MIN(A9,25)-20)+3.5*MAX(0,MIN(A9,30)-25)+4*MAX(0,MIN(A9,35)-30)+4.5*MAX(0,MIN(A9,50)-35)+5*MAX(0,A9-50)+IF(A9<=20,55,IF(A9<=30,60,IF(A9<=40,65,IF(A9<=50,70,75))))+4.9*A9 -> 141.5 | D9: =30+3*MAX(0,MIN(A9,5)-2)+4*MAX(0,MIN(A9,9)-5)+4.5*MAX(0,MIN(A9,14)-9)+5.5*MAX(0,MIN(A9,20)-14)+6.5*MAX(0,MIN(A9,27)-20)+7.5*MAX(0,A9-27)+55+1.5*MAX(0,MIN(A9,8)-5)+2*MAX(0,MIN(A9,15)-8)+2.5*MAX(0,MIN(A9,20)-15)+3*MAX(0,MIN(A9,25)-20)+3.5*MAX(0,A9-25)+100+4.9*A9 -> 272 | E9: =C9/B9-1 -> 0.50531915 | F9: =D9/B9-1 -> 1.893617
A10: 12 | B10: =25+1*MAX(0,MIN(A10,20)-10)+2*MAX(0,MIN(A10,50)-20)+3*MAX(0,A10-50)+20+4.9*A10 -> 105.8 | C10: =30+1.5*MAX(0,MIN(A10,10)-5)+2*MAX(0,MIN(A10,15)-10)+2.5*MAX(0,MIN(A10,20)-15)+3*MAX(0,MIN(A10,25)-20)+3.5*MAX(0,MIN(A10,30)-25)+4*MAX(0,MIN(A10,35)-30)+4.5*MAX(0,MIN(A10,50)-35)+5*MAX(0,A10-50)+IF(A10<=20,55,IF(A10<=30,60,IF(A10<=40,65,IF(A10<=50,70,75))))+4.9*A10 -> 155.3 | D10: =30+3*MAX(0,MIN(A10,5)-2)+4*MAX(0,MIN(A10,9)-5)+4.5*MAX(0,MIN(A10,14)-9)+5.5*MAX(0,MIN(A10,20)-14)+6.5*MAX(0,MIN(A10,27)-20)+7.5*MAX(0,A10-27)+55+1.5*MAX(0,MIN(A10,8)-5)+2*MAX(0,MIN(A10,15)-8)+2.5*MAX(0,MIN(A10,20)-15)+3*MAX(0,MIN(A10,25)-20)+3.5*MAX(0,A10-25)+100+4.9*A10 -> 294.8 | E10: =C10/B10-1 -> 0.46786389 | F10: =D10/B10-1 -> 1.7863894 | G10: Normal usage + daughter
A11: 15 | B11: =25+1*MAX(0,MIN(A11,20)-10)+2*MAX(0,MIN(A11,50)-20)+3*MAX(0,A11-50)+20+4.9*A11 -> 123.5 | C11: =30+1.5*MAX(0,MIN(A11,10)-5)+2*MAX(0,MIN(A11,15)-10)+2.5*MAX(0,MIN(A11,20)-15)+3*MAX(0,MIN(A11,25)-20)+3.5*MAX(0,MIN(A11,30)-25)+4*MAX(0,MIN(A11,35)-30)+4.5*MAX(0,MIN(A11,50)-35)+5*MAX(0,A11-50)+IF(A11<=20,55,IF(A11<=30,60,IF(A11<=40,65,IF(A11<=50,70,75))))+4.9*A11 -> 176 | D11: =30+3*MAX(0,MIN(A11,5)-2)+4*MAX(0,MIN(A11,9)-5)+4.5*MAX(0,MIN(A11,14)-9)+5.5*MAX(0,MIN(A11,20)-14)+6.5*MAX(0,MIN(A11,27)-20)+7.5*MAX(0,A11-27)+55+1.5*MAX(0,MIN(A11,8)-5)+2*MAX(0,MIN(A11,15)-8)+2.5*MAX(0,MIN(A11,20)-15)+3*MAX(0,MIN(A11,25)-20)+3.5*MAX(0,A11-25)+100+4.9*A11 -> 330 | E11: =C11/B11-1 -> 0.42510121 | F11: =D11/B11-1 -> 1.6720648
A12: 18 | B12: =25+1*MAX(0,MIN(A12,20)-10)+2*MAX(0,MIN(A12,50)-20)+3*MAX(0,A12-50)+20+4.9*A12 -> 141.2 | C12: =30+1.5*MAX(0,MIN(A12,10)-5)+2*MAX(0,MIN(A12,15)-10)+2.5*MAX(0,MIN(A12,20)-15)+3*MAX(0,MIN(A12,25)-20)+3.5*MAX(0,MIN(A12,30)-25)+4*MAX(0,MIN(A12,35)-30)+4.5*MAX(0,MIN(A12,50)-35)+5*MAX(0,A12-50)+IF(A12<=20,55,IF(A12<=30,60,IF(A12<=40,65,IF(A12<=50,70,75))))+4.9*A12 -> 198.2 | D12: =30+3*MAX(0,MIN(A12,5)-2)+4*MAX(0,MIN(A12,9)-5)+4.5*MAX(0,MIN(A12,14)-9)+5.5*MAX(0,MIN(A12,20)-14)+6.5*MAX(0,MIN(A12,27)-20)+7.5*MAX(0,A12-27)+55+1.5*MAX(0,MIN(A12,8)-5)+2*MAX(0,MIN(A12,15)-8)+2.5*MAX(0,MIN(A12,20)-15)+3*MAX(0,MIN(A12,25)-20)+3.5*MAX(0,A12-25)+100+4.9*A12 -> 368.7 | E12: =C12/B12-1 -> 0.40368272 | F12: =D12/B12-1 -> 1.6111898
A13: 20 | B13: =25+1*MAX(0,MIN(A13,20)-10)+2*MAX(0,MIN(A13,50)-20)+3*MAX(0,A13-50)+20+4.9*A13 -> 153 | C13: =30+1.5*MAX(0,MIN(A13,10)-5)+2*MAX(0,MIN(A13,15)-10)+2.5*MAX(0,MIN(A13,20)-15)+3*MAX(0,MIN(A13,25)-20)+3.5*MAX(0,MIN(A13,30)-25)+4*MAX(0,MIN(A13,35)-30)+4.5*MAX(0,MIN(A13,50)-35)+5*MAX(0,A13-50)+IF(A13<=20,55,IF(A13<=30,60,IF(A13<=40,65,IF(A13<=50,70,75))))+4.9*A13 -> 213 | D13: =30+3*MAX(0,MIN(A13,5)-2)+4*MAX(0,MIN(A13,9)-5)+4.5*MAX(0,MIN(A13,14)-9)+5.5*MAX(0,MIN(A13,20)-14)+6.5*MAX(0,MIN(A13,27)-20)+7.5*MAX(0,A13-27)+55+1.5*MAX(0,MIN(A13,8)-5)+2*MAX(0,MIN(A13,15)-8)+2.5*MAX(0,MIN(A13,20)-15)+3*MAX(0,MIN(A13,25)-20)+3.5*MAX(0,A13-25)+100+4.9*A13 -> 394.5 | E13: =C13/B13-1 -> 0.39215686 | F13: =D13/B13-1 -> 1.5784314
A14: 22 | B14: =25+1*MAX(0,MIN(A14,20)-10)+2*MAX(0,MIN(A14,50)-20)+3*MAX(0,A14-50)+20+4.9*A14 -> 166.8 | C14: =30+1.5*MAX(0,MIN(A14,10)-5)+2*MAX(0,MIN(A14,15)-10)+2.5*MAX(0,MIN(A14,20)-15)+3*MAX(0,MIN(A14,25)-20)+3.5*MAX(0,MIN(A14,30)-25)+4*MAX(0,MIN(A14,35)-30)+4.5*MAX(0,MIN(A14,50)-35)+5*MAX(0,A14-50)+IF(A14<=20,55,IF(A14<=30,60,IF(A14<=40,65,IF(A14<=50,70,75))))+4.9*A14 -> 233.8 | D14: =30+3*MAX(0,MIN(A14,5)-2)+4*MAX(0,MIN(A14,9)-5)+4.5*MAX(0,MIN(A14,14)-9)+5.5*MAX(0,MIN(A14,20)-14)+6.5*MAX(0,MIN(A14,27)-20)+7.5*MAX(0,A14-27)+55+1.5*MAX(0,MIN(A14,8)-5)+2*MAX(0,MIN(A14,15)-8)+2.5*MAX(0,MIN(A14,20)-15)+3*MAX(0,MIN(A14,25)-20)+3.5*MAX(0,A14-25)+100+4.9*A14 -> 423.3 | E14: =C14/B14-1 -> 0.40167866 | F14: =D14/B14-1 -> 1.5377698
A15: 24 | B15: =25+1*MAX(0,MIN(A15,20)-10)+2*MAX(0,MIN(A15,50)-20)+3*MAX(0,A15-50)+20+4.9*A15 -> 180.6 | C15: =30+1.5*MAX(0,MIN(A15,10)-5)+2*MAX(0,MIN(A15,15)-10)+2.5*MAX(0,MIN(A15,20)-15)+3*MAX(0,MIN(A15,25)-20)+3.5*MAX(0,MIN(A15,30)-25)+4*MAX(0,MIN(A15,35)-30)+4.5*MAX(0,MIN(A15,50)-35)+5*MAX(0,A15-50)+IF(A15<=20,55,IF(A15<=30,60,IF(A15<=40,65,IF(A15<=50,70,75))))+4.9*A15 -> 249.6 | D15: =30+3*MAX(0,MIN(A15,5)-2)+4*MAX(0,MIN(A15,9)-5)+4.5*MAX(0,MIN(A15,14)-9)+5.5*MAX(0,MIN(A15,20)-14)+6.5*MAX(0,MIN(A15,27)-20)+7.5*MAX(0,A15-27)+55+1.5*MAX(0,MIN(A15,8)-5)+2*MAX(0,MIN(A15,15)-8)+2.5*MAX(0,MIN(A15,20)-15)+3*MAX(0,MIN(A15,25)-20)+3.5*MAX(0,A15-25)+100+4.9*A15 -> 452.1 | E15: =C15/B15-1 -> 0.3820598 | F15: =D15/B15-1 -> 1.5033223 | G15: Your July 2026 (irrigation overuse)
A16: 30 | B16: =25+1*MAX(0,MIN(A16,20)-10)+2*MAX(0,MIN(A16,50)-20)+3*MAX(0,A16-50)+20+4.9*A16 -> 222 | C16: =30+1.5*MAX(0,MIN(A16,10)-5)+2*MAX(0,MIN(A16,15)-10)+2.5*MAX(0,MIN(A16,20)-15)+3*MAX(0,MIN(A16,25)-20)+3.5*MAX(0,MIN(A16,30)-25)+4*MAX(0,MIN(A16,35)-30)+4.5*MAX(0,MIN(A16,50)-35)+5*MAX(0,A16-50)+IF(A16<=20,55,IF(A16<=30,60,IF(A16<=40,65,IF(A16<=50,70,75))))+4.9*A16 -> 299.5 | D16: =30+3*MAX(0,MIN(A16,5)-2)+4*MAX(0,MIN(A16,9)-5)+4.5*MAX(0,MIN(A16,14)-9)+5.5*MAX(0,MIN(A16,20)-14)+6.5*MAX(0,MIN(A16,27)-20)+7.5*MAX(0,A16-27)+55+1.5*MAX(0,MIN(A16,8)-5)+2*MAX(0,MIN(A16,15)-8)+2.5*MAX(0,MIN(A16,20)-15)+3*MAX(0,MIN(A16,25)-20)+3.5*MAX(0,A16-25)+100+4.9*A16 -> 544 | E16: =C16/B16-1 -> 0.3490991 | F16: =D16/B16-1 -> 1.4504505
A18: Rate definitions (from handout pages 4 & 6): S1 water $30 base incl 5k, tiers $1.50/$2/$2.50/$3/$3.50/$4/$4.50, >50k $5 (40-50k not printed; $4.50 assumed). S1 sewer flat by usage: $55 to 20k, $60 to 30k, $65 to 40k, $70 to 50k, $75 above.
A19: S2 water $30 base incl 2k, tiers $3/$4/$4.50/$5.50/$6.50, >27k $7.50. S2 sewer $55 base incl 5k + $1.50/$2/$2.50/$3/$3.50 volumetric tiers + $100/mo Capital Project Base Fee per connection.
A21: DISTRICT CONTEXT (handout p.2, current usage distribution across 679 residential meters):
A22: Bracket | B22: # Meters | C22: % of District
A23: <6k | B23: 38 | C23: =B23/679 -> 0.055964654
A24: 6k-10k | B24: 142 | C24: =B24/679 -> 0.20913108
A25: 10k-15k | B25: 200 | C25: =B25/679 -> 0.29455081
A26: 15k-20k | B26: 158 | C26: =B26/679 -> 0.23269514
A27: 20k-25k | B27: 84 | C27: =B27/679 -> 0.12371134
A28: 25k-30k | B28: 37 | C28: =B28/679 -> 0.0544919
A29: 30k-40k | B29: 11 | C29: =B29/679 -> 0.016200295
A30: 40k-50k | B30: 4 | C30: =B30/679 -> 0.0058910162
A31: >50k | B31: 5 | C31: =B31/679 -> 0.0073637703
A33: 27% of homes use <10k/month (bills ~$60-79 all-in today) - the $80 neighbor at 3918 is one of 180 such homes, using ~7k gal. Your July 2026 (24k) is in roughly the top 15% of meters. Your pre-2026 median (~9-10k) was typical.
A34: FY27 proposed budget W+WW revenue = $950,922 = EXACTLY Scenario 1 projected service revenue -> board leaning Scenario 1 now, second-phase increase 2028, $100 fee held in reserve. FY27 budget also carries $150,000 for PUC Appeal - district expects a challenge.
A35: Commercial correction (both scenarios): Walgreens total today $10/mo -> ~$180-195; car wash $418 -> ~$1,097-1,800. Cost shifting: constable patrol (~$308k), streetlights (~$142k), reclaimed irrigation move to HOA - expect HOA dues to rise.

Sheet Counter-Proposal S3
A1: Counter-Proposal "Scenario 3" - Same Revenue as S1, Fairer Distribution
A2: Calibrated on the district's own 679-meter usage distribution to produce the same total service revenue as EVO Scenario 1. Blue cells are the proposed rate levers - change them and everything recomputes.
A4: S3 RATE LEVERS | D4: REVENUE CHECK (bracket midpoints x meter counts, annualized)
A5: Water base (incl 3k gal) | B5: 15 | D5: Bracket | E5: Midpoint kGal | F5: Meters | G5: Current $/mo | H5: S1 $/mo | I5: S3 $/mo
A6: Water 3-10k $/kGal | B6: 0.85 | D6: <6k | E6: 4 | F6: 38 | G6: =25+1*MAX(0,MIN($E6,20)-10)+2*MAX(0,MIN($E6,50)-20)+3*MAX(0,$E6-50)+20 -> 45 | H6: =30+1.5*MAX(0,MIN($E6,10)-5)+2*MAX(0,MIN($E6,15)-10)+2.5*MAX(0,MIN($E6,20)-15)+3*MAX(0,MIN($E6,25)-20)+3.5*MAX(0,MIN($E6,30)-25)+4*MAX(0,MIN($E6,35)-30)+4.5*MAX(0,MIN($E6,50)-35)+5*MAX(0,$E6-50)+IF($E6<=20,55,IF($E6<=30,60,IF($E6<=40,65,IF($E6<=50,70,75)))) -> 85 | I6: =$B$5+$B$6*MAX(0,MIN($E6,10)-3)+$B$7*MAX(0,MIN($E6,15)-10)+$B$8*MAX(0,MIN($E6,20)-15)+$B$9*MAX(0,MIN($E6,30)-20)+$B$10*MAX(0,$E6-30)+$B$11+$B$12*MIN(MAX($E6-3,0),$B$13-3) -> 47.1
A7: Water 10-15k | B7: 1.7 | D7: 6k-10k | E7: 8 | F7: 142 | G7: =25+1*MAX(0,MIN($E7,20)-10)+2*MAX(0,MIN($E7,50)-20)+3*MAX(0,$E7-50)+20 -> 45 | H7: =30+1.5*MAX(0,MIN($E7,10)-5)+2*MAX(0,MIN($E7,15)-10)+2.5*MAX(0,MIN($E7,20)-15)+3*MAX(0,MIN($E7,25)-20)+3.5*MAX(0,MIN($E7,30)-25)+4*MAX(0,MIN($E7,35)-30)+4.5*MAX(0,MIN($E7,50)-35)+5*MAX(0,$E7-50)+IF($E7<=20,55,IF($E7<=30,60,IF($E7<=40,65,IF($E7<=50,70,75)))) -> 89.5 | I7: =$B$5+$B$6*MAX(0,MIN($E7,10)-3)+$B$7*MAX(0,MIN($E7,15)-10)+$B$8*MAX(0,MIN($E7,20)-15)+$B$9*MAX(0,MIN($E7,30)-20)+$B$10*MAX(0,$E7-30)+$B$11+$B$12*MIN(MAX($E7-3,0),$B$13-3) -> 55.5
A8: Water 15-20k | B8: 3 | D8: 10k-15k | E8: 12.5 | F8: 200 | G8: =25+1*MAX(0,MIN($E8,20)-10)+2*MAX(0,MIN($E8,50)-20)+3*MAX(0,$E8-50)+20 -> 47.5 | H8: =30+1.5*MAX(0,MIN($E8,10)-5)+2*MAX(0,MIN($E8,15)-10)+2.5*MAX(0,MIN($E8,20)-15)+3*MAX(0,MIN($E8,25)-20)+3.5*MAX(0,MIN($E8,30)-25)+4*MAX(0,MIN($E8,35)-30)+4.5*MAX(0,MIN($E8,50)-35)+5*MAX(0,$E8-50)+IF($E8<=20,55,IF($E8<=30,60,IF($E8<=40,65,IF($E8<=50,70,75)))) -> 97.5 | I8: =$B$5+$B$6*MAX(0,MIN($E8,10)-3)+$B$7*MAX(0,MIN($E8,15)-10)+$B$8*MAX(0,MIN($E8,20)-15)+$B$9*MAX(0,MIN($E8,30)-20)+$B$10*MAX(0,$E8-30)+$B$11+$B$12*MIN(MAX($E8-3,0),$B$13-3) -> 67.075
A9: Water 20-30k | B9: 6 | D9: 15k-20k | E9: 17.5 | F9: 158 | G9: =25+1*MAX(0,MIN($E9,20)-10)+2*MAX(0,MIN($E9,50)-20)+3*MAX(0,$E9-50)+20 -> 52.5 | H9: =30+1.5*MAX(0,MIN($E9,10)-5)+2*MAX(0,MIN($E9,15)-10)+2.5*MAX(0,MIN($E9,20)-15)+3*MAX(0,MIN($E9,25)-20)+3.5*MAX(0,MIN($E9,30)-25)+4*MAX(0,MIN($E9,35)-30)+4.5*MAX(0,MIN($E9,50)-35)+5*MAX(0,$E9-50)+IF($E9<=20,55,IF($E9<=30,60,IF($E9<=40,65,IF($E9<=50,70,75)))) -> 108.75 | I9: =$B$5+$B$6*MAX(0,MIN($E9,10)-3)+$B$7*MAX(0,MIN($E9,15)-10)+$B$8*MAX(0,MIN($E9,20)-15)+$B$9*MAX(0,MIN($E9,30)-20)+$B$10*MAX(0,$E9-30)+$B$11+$B$12*MIN(MAX($E9-3,0),$B$13-3) -> 81.95
A10: Water >30k | B10: 8 | D10: 20k-25k | E10: 22.5 | F10: 84 | G10: =25+1*MAX(0,MIN($E10,20)-10)+2*MAX(0,MIN($E10,50)-20)+3*MAX(0,$E10-50)+20 -> 60 | H10: =30+1.5*MAX(0,MIN($E10,10)-5)+2*MAX(0,MIN($E10,15)-10)+2.5*MAX(0,MIN($E10,20)-15)+3*MAX(0,MIN($E10,25)-20)+3.5*MAX(0,MIN($E10,30)-25)+4*MAX(0,MIN($E10,35)-30)+4.5*MAX(0,MIN($E10,50)-35)+5*MAX(0,$E10-50)+IF($E10<=20,55,IF($E10<=30,60,IF($E10<=40,65,IF($E10<=50,70,75)))) -> 127.5 | I10: =$B$5+$B$6*MAX(0,MIN($E10,10)-3)+$B$7*MAX(0,MIN($E10,15)-10)+$B$8*MAX(0,MIN($E10,20)-15)+$B$9*MAX(0,MIN($E10,30)-20)+$B$10*MAX(0,$E10-30)+$B$11+$B$12*MIN(MAX($E10-3,0),$B$13-3) -> 104.45
A11: Sewer base | B11: 30 | D11: 25k-30k | E11: 27.5 | F11: 37 | G11: =25+1*MAX(0,MIN($E11,20)-10)+2*MAX(0,MIN($E11,50)-20)+3*MAX(0,$E11-50)+20 -> 70 | H11: =30+1.5*MAX(0,MIN($E11,10)-5)+2*MAX(0,MIN($E11,15)-10)+2.5*MAX(0,MIN($E11,20)-15)+3*MAX(0,MIN($E11,25)-20)+3.5*MAX(0,MIN($E11,30)-25)+4*MAX(0,MIN($E11,35)-30)+4.5*MAX(0,MIN($E11,50)-35)+5*MAX(0,$E11-50)+IF($E11<=20,55,IF($E11<=30,60,IF($E11<=40,65,IF($E11<=50,70,75)))) -> 143.75 | I11: =$B$5+$B$6*MAX(0,MIN($E11,10)-3)+$B$7*MAX(0,MIN($E11,15)-10)+$B$8*MAX(0,MIN($E11,20)-15)+$B$9*MAX(0,MIN($E11,30)-20)+$B$10*MAX(0,$E11-30)+$B$11+$B$12*MIN(MAX($E11-3,0),$B$13-3) -> 134.45
A12: Sewer $/kGal on 3-15k band | B12: 1.25 | D12: 30k-40k | E12: 35 | F12: 11 | G12: =25+1*MAX(0,MIN($E12,20)-10)+2*MAX(0,MIN($E12,50)-20)+3*MAX(0,$E12-50)+20 -> 85 | H12: =30+1.5*MAX(0,MIN($E12,10)-5)+2*MAX(0,MIN($E12,15)-10)+2.5*MAX(0,MIN($E12,20)-15)+3*MAX(0,MIN($E12,25)-20)+3.5*MAX(0,MIN($E12,30)-25)+4*MAX(0,MIN($E12,35)-30)+4.5*MAX(0,MIN($E12,50)-35)+5*MAX(0,$E12-50)+IF($E12<=20,55,IF($E12<=30,60,IF($E12<=40,65,IF($E12<=50,70,75)))) -> 177.5 | I12: =$B$5+$B$6*MAX(0,MIN($E12,10)-3)+$B$7*MAX(0,MIN($E12,15)-10)+$B$8*MAX(0,MIN($E12,20)-15)+$B$9*MAX(0,MIN($E12,30)-20)+$B$10*MAX(0,$E12-30)+$B$11+$B$12*MIN(MAX($E12-3,0),$B$13-3) -> 189.45
A13: Sewer volumetric cap | B13: 15 | D13: 40k-50k | E13: 45 | F13: 4 | G13: =25+1*MAX(0,MIN($E13,20)-10)+2*MAX(0,MIN($E13,50)-20)+3*MAX(0,$E13-50)+20 -> 105 | H13: =30+1.5*MAX(0,MIN($E13,10)-5)+2*MAX(0,MIN($E13,15)-10)+2.5*MAX(0,MIN($E13,20)-15)+3*MAX(0,MIN($E13,25)-20)+3.5*MAX(0,MIN($E13,30)-25)+4*MAX(0,MIN($E13,35)-30)+4.5*MAX(0,MIN($E13,50)-35)+5*MAX(0,$E13-50)+IF($E13<=20,55,IF($E13<=30,60,IF($E13<=40,65,IF($E13<=50,70,75)))) -> 227.5 | I13: =$B$5+$B$6*MAX(0,MIN($E13,10)-3)+$B$7*MAX(0,MIN($E13,15)-10)+$B$8*MAX(0,MIN($E13,20)-15)+$B$9*MAX(0,MIN($E13,30)-20)+$B$10*MAX(0,$E13-30)+$B$11+$B$12*MIN(MAX($E13-3,0),$B$13-3) -> 269.45
A14: M&O tax increase ($/100 valuation) | B14: 0.045 | D14: >50k | E14: 55 | F14: 5 | G14: =25+1*MAX(0,MIN($E14,20)-10)+2*MAX(0,MIN($E14,50)-20)+3*MAX(0,$E14-50)+20 -> 130 | H14: =30+1.5*MAX(0,MIN($E14,10)-5)+2*MAX(0,MIN($E14,15)-10)+2.5*MAX(0,MIN($E14,20)-15)+3*MAX(0,MIN($E14,25)-20)+3.5*MAX(0,MIN($E14,30)-25)+4*MAX(0,MIN($E14,35)-30)+4.5*MAX(0,MIN($E14,50)-35)+5*MAX(0,$E14-50)+IF($E14<=20,55,IF($E14<=30,60,IF($E14<=40,65,IF($E14<=50,70,75)))) -> 280 | I14: =$B$5+$B$6*MAX(0,MIN($E14,10)-3)+$B$7*MAX(0,MIN($E14,15)-10)+$B$8*MAX(0,MIN($E14,20)-15)+$B$9*MAX(0,MIN($E14,30)-20)+$B$10*MAX(0,$E14-30)+$B$11+$B$12*MIN(MAX($E14-3,0),$B$13-3) -> 349.45
A15: Commercial uplift vs S1 | B15: 0.25 | D15: Residential annual | G15: =SUMPRODUCT($F$6:$F$14,G6:G14)*12 -> 426360 | H15: =SUMPRODUCT($F$6:$F$14,H6:H14)*12 -> 874953 | I15: =SUMPRODUCT($F$6:$F$14,I6:I14)*12 -> 656296.2
D16: Commercial annual (9 accounts, handout p.2/4) | H16: =4947.5*12 -> 59370 | I16: =4947.5*12*(1+$B$15) -> 74212.5
D17: Tax component (+rate x $466,651,883 x 98%) | I17: =466651883/100*$B$14*0.98 -> 205793.48
D18: TOTAL | H18: =H15+H16 -> 934323 | I18: =I15+I16+I17 -> 936302.18 | J18: =I18-H18 -> 1979.1804 | K18: <- S3 minus S1: target $0
A21: HOUSEHOLD IMPACT (water+sewer only; NFBWA $4.90/kGal identical in every scenario; S3 tax ~$28/mo avg homestead shown separately)
A22: Usage kGal | B22: Current | C22: S1 | D22: S3 | E22: S1 vs Cur | F22: S3 vs Cur | G22: Who this is
A23: 4 | B23: =25+1*MAX(0,MIN($A23,20)-10)+2*MAX(0,MIN($A23,50)-20)+3*MAX(0,$A23-50)+20 -> 45 | C23: =30+1.5*MAX(0,MIN($A23,10)-5)+2*MAX(0,MIN($A23,15)-10)+2.5*MAX(0,MIN($A23,20)-15)+3*MAX(0,MIN($A23,25)-20)+3.5*MAX(0,MIN($A23,30)-25)+4*MAX(0,MIN($A23,35)-30)+4.5*MAX(0,MIN($A23,50)-35)+5*MAX(0,$A23-50)+IF($A23<=20,55,IF($A23<=30,60,IF($A23<=40,65,IF($A23<=50,70,75)))) -> 85 | D23: =$B$5+$B$6*MAX(0,MIN($A23,10)-3)+$B$7*MAX(0,MIN($A23,15)-10)+$B$8*MAX(0,MIN($A23,20)-15)+$B$9*MAX(0,MIN($A23,30)-20)+$B$10*MAX(0,$A23-30)+$B$11+$B$12*MIN(MAX($A23-3,0),$B$13-3) -> 47.1 | E23: =C23/B23-1 -> 0.88888889 | F23: =D23/B23-1 -> 0.046666667 | G23: true low user (38 homes)
A24: 7 | B24: =25+1*MAX(0,MIN($A24,20)-10)+2*MAX(0,MIN($A24,50)-20)+3*MAX(0,$A24-50)+20 -> 45 | C24: =30+1.5*MAX(0,MIN($A24,10)-5)+2*MAX(0,MIN($A24,15)-10)+2.5*MAX(0,MIN($A24,20)-15)+3*MAX(0,MIN($A24,25)-20)+3.5*MAX(0,MIN($A24,30)-25)+4*MAX(0,MIN($A24,35)-30)+4.5*MAX(0,MIN($A24,50)-35)+5*MAX(0,$A24-50)+IF($A24<=20,55,IF($A24<=30,60,IF($A24<=40,65,IF($A24<=50,70,75)))) -> 88 | D24: =$B$5+$B$6*MAX(0,MIN($A24,10)-3)+$B$7*MAX(0,MIN($A24,15)-10)+$B$8*MAX(0,MIN($A24,20)-15)+$B$9*MAX(0,MIN($A24,30)-20)+$B$10*MAX(0,$A24-30)+$B$11+$B$12*MIN(MAX($A24-3,0),$B$13-3) -> 53.4 | E24: =C24/B24-1 -> 0.95555556 | F24: =D24/B24-1 -> 0.18666667 | G24: neighbor at 3918 / your low months
A25: 8 | B25: =25+1*MAX(0,MIN($A25,20)-10)+2*MAX(0,MIN($A25,50)-20)+3*MAX(0,$A25-50)+20 -> 45 | C25: =30+1.5*MAX(0,MIN($A25,10)-5)+2*MAX(0,MIN($A25,15)-10)+2.5*MAX(0,MIN($A25,20)-15)+3*MAX(0,MIN($A25,25)-20)+3.5*MAX(0,MIN($A25,30)-25)+4*MAX(0,MIN($A25,35)-30)+4.5*MAX(0,MIN($A25,50)-35)+5*MAX(0,$A25-50)+IF($A25<=20,55,IF($A25<=30,60,IF($A25<=40,65,IF($A25<=50,70,75)))) -> 89.5 | D25: =$B$5+$B$6*MAX(0,MIN($A25,10)-3)+$B$7*MAX(0,MIN($A25,15)-10)+$B$8*MAX(0,MIN($A25,20)-15)+$B$9*MAX(0,MIN($A25,30)-20)+$B$10*MAX(0,$A25-30)+$B$11+$B$12*MIN(MAX($A25-3,0),$B$13-3) -> 55.5 | E25: =C25/B25-1 -> 0.98888889 | F25: =D25/B25-1 -> 0.23333333 | G25: your normal month
A26: 12.5 | B26: =25+1*MAX(0,MIN($A26,20)-10)+2*MAX(0,MIN($A26,50)-20)+3*MAX(0,$A26-50)+20 -> 47.5 | C26: =30+1.5*MAX(0,MIN($A26,10)-5)+2*MAX(0,MIN($A26,15)-10)+2.5*MAX(0,MIN($A26,20)-15)+3*MAX(0,MIN($A26,25)-20)+3.5*MAX(0,MIN($A26,30)-25)+4*MAX(0,MIN($A26,35)-30)+4.5*MAX(0,MIN($A26,50)-35)+5*MAX(0,$A26-50)+IF($A26<=20,55,IF($A26<=30,60,IF($A26<=40,65,IF($A26<=50,70,75)))) -> 97.5 | D26: =$B$5+$B$6*MAX(0,MIN($A26,10)-3)+$B$7*MAX(0,MIN($A26,15)-10)+$B$8*MAX(0,MIN($A26,20)-15)+$B$9*MAX(0,MIN($A26,30)-20)+$B$10*MAX(0,$A26-30)+$B$11+$B$12*MIN(MAX($A26-3,0),$B$13-3) -> 67.075 | E26: =C26/B26-1 -> 1.0526316 | F26: =D26/B26-1 -> 0.41210526 | G26: district median
A27: 17.5 | B27: =25+1*MAX(0,MIN($A27,20)-10)+2*MAX(0,MIN($A27,50)-20)+3*MAX(0,$A27-50)+20 -> 52.5 | C27: =30+1.5*MAX(0,MIN($A27,10)-5)+2*MAX(0,MIN($A27,15)-10)+2.5*MAX(0,MIN($A27,20)-15)+3*MAX(0,MIN($A27,25)-20)+3.5*MAX(0,MIN($A27,30)-25)+4*MAX(0,MIN($A27,35)-30)+4.5*MAX(0,MIN($A27,50)-35)+5*MAX(0,$A27-50)+IF($A27<=20,55,IF($A27<=30,60,IF($A27<=40,65,IF($A27<=50,70,75)))) -> 108.75 | D27: =$B$5+$B$6*MAX(0,MIN($A27,10)-3)+$B$7*MAX(0,MIN($A27,15)-10)+$B$8*MAX(0,MIN($A27,20)-15)+$B$9*MAX(0,MIN($A27,30)-20)+$B$10*MAX(0,$A27-30)+$B$11+$B$12*MIN(MAX($A27-3,0),$B$13-3) -> 81.95 | E27: =C27/B27-1 -> 1.0714286 | F27: =D27/B27-1 -> 0.56095238
A28: 22.5 | B28: =25+1*MAX(0,MIN($A28,20)-10)+2*MAX(0,MIN($A28,50)-20)+3*MAX(0,$A28-50)+20 -> 60 | C28: =30+1.5*MAX(0,MIN($A28,10)-5)+2*MAX(0,MIN($A28,15)-10)+2.5*MAX(0,MIN($A28,20)-15)+3*MAX(0,MIN($A28,25)-20)+3.5*MAX(0,MIN($A28,30)-25)+4*MAX(0,MIN($A28,35)-30)+4.5*MAX(0,MIN($A28,50)-35)+5*MAX(0,$A28-50)+IF($A28<=20,55,IF($A28<=30,60,IF($A28<=40,65,IF($A28<=50,70,75)))) -> 127.5 | D28: =$B$5+$B$6*MAX(0,MIN($A28,10)-3)+$B$7*MAX(0,MIN($A28,15)-10)+$B$8*MAX(0,MIN($A28,20)-15)+$B$9*MAX(0,MIN($A28,30)-20)+$B$10*MAX(0,$A28-30)+$B$11+$B$12*MIN(MAX($A28-3,0),$B$13-3) -> 104.45 | E28: =C28/B28-1 -> 1.125 | F28: =D28/B28-1 -> 0.74083333
A29: 24 | B29: =25+1*MAX(0,MIN($A29,20)-10)+2*MAX(0,MIN($A29,50)-20)+3*MAX(0,$A29-50)+20 -> 63 | C29: =30+1.5*MAX(0,MIN($A29,10)-5)+2*MAX(0,MIN($A29,15)-10)+2.5*MAX(0,MIN($A29,20)-15)+3*MAX(0,MIN($A29,25)-20)+3.5*MAX(0,MIN($A29,30)-25)+4*MAX(0,MIN($A29,35)-30)+4.5*MAX(0,MIN($A29,50)-35)+5*MAX(0,$A29-50)+IF($A29<=20,55,IF($A29<=30,60,IF($A29<=40,65,IF($A29<=50,70,75)))) -> 132 | D29: =$B$5+$B$6*MAX(0,MIN($A29,10)-3)+$B$7*MAX(0,MIN($A29,15)-10)+$B$8*MAX(0,MIN($A29,20)-15)+$B$9*MAX(0,MIN($A29,30)-20)+$B$10*MAX(0,$A29-30)+$B$11+$B$12*MIN(MAX($A29-3,0),$B$13-3) -> 113.45 | E29: =C29/B29-1 -> 1.0952381 | F29: =D29/B29-1 -> 0.80079365 | G29: your July 2026 (irrigation overuse)
A30: 27.5 | B30: =25+1*MAX(0,MIN($A30,20)-10)+2*MAX(0,MIN($A30,50)-20)+3*MAX(0,$A30-50)+20 -> 70 | C30: =30+1.5*MAX(0,MIN($A30,10)-5)+2*MAX(0,MIN($A30,15)-10)+2.5*MAX(0,MIN($A30,20)-15)+3*MAX(0,MIN($A30,25)-20)+3.5*MAX(0,MIN($A30,30)-25)+4*MAX(0,MIN($A30,35)-30)+4.5*MAX(0,MIN($A30,50)-35)+5*MAX(0,$A30-50)+IF($A30<=20,55,IF($A30<=30,60,IF($A30<=40,65,IF($A30<=50,70,75)))) -> 143.75 | D30: =$B$5+$B$6*MAX(0,MIN($A30,10)-3)+$B$7*MAX(0,MIN($A30,15)-10)+$B$8*MAX(0,MIN($A30,20)-15)+$B$9*MAX(0,MIN($A30,30)-20)+$B$10*MAX(0,$A30-30)+$B$11+$B$12*MIN(MAX($A30-3,0),$B$13-3) -> 134.45 | E30: =C30/B30-1 -> 1.0535714 | F30: =D30/B30-1 -> 0.92071429
A31: 35 | B31: =25+1*MAX(0,MIN($A31,20)-10)+2*MAX(0,MIN($A31,50)-20)+3*MAX(0,$A31-50)+20 -> 85 | C31: =30+1.5*MAX(0,MIN($A31,10)-5)+2*MAX(0,MIN($A31,15)-10)+2.5*MAX(0,MIN($A31,20)-15)+3*MAX(0,MIN($A31,25)-20)+3.5*MAX(0,MIN($A31,30)-25)+4*MAX(0,MIN($A31,35)-30)+4.5*MAX(0,MIN($A31,50)-35)+5*MAX(0,$A31-50)+IF($A31<=20,55,IF($A31<=30,60,IF($A31<=40,65,IF($A31<=50,70,75)))) -> 177.5 | D31: =$B$5+$B$6*MAX(0,MIN($A31,10)-3)+$B$7*MAX(0,MIN($A31,15)-10)+$B$8*MAX(0,MIN($A31,20)-15)+$B$9*MAX(0,MIN($A31,30)-20)+$B$10*MAX(0,$A31-30)+$B$11+$B$12*MIN(MAX($A31-3,0),$B$13-3) -> 189.45 | E31: =C31/B31-1 -> 1.0882353 | F31: =D31/B31-1 -> 1.2288235 | G31: heavy user - pays MORE than under S1
A32: 45 | B32: =25+1*MAX(0,MIN($A32,20)-10)+2*MAX(0,MIN($A32,50)-20)+3*MAX(0,$A32-50)+20 -> 105 | C32: =30+1.5*MAX(0,MIN($A32,10)-5)+2*MAX(0,MIN($A32,15)-10)+2.5*MAX(0,MIN($A32,20)-15)+3*MAX(0,MIN($A32,25)-20)+3.5*MAX(0,MIN($A32,30)-25)+4*MAX(0,MIN($A32,35)-30)+4.5*MAX(0,MIN($A32,50)-35)+5*MAX(0,$A32-50)+IF($A32<=20,55,IF($A32<=30,60,IF($A32<=40,65,IF($A32<=50,70,75)))) -> 227.5 | D32: =$B$5+$B$6*MAX(0,MIN($A32,10)-3)+$B$7*MAX(0,MIN($A32,15)-10)+$B$8*MAX(0,MIN($A32,20)-15)+$B$9*MAX(0,MIN($A32,30)-20)+$B$10*MAX(0,$A32-30)+$B$11+$B$12*MIN(MAX($A32-3,0),$B$13-3) -> 269.45 | E32: =C32/B32-1 -> 1.1666667 | F32: =D32/B32-1 -> 1.5661905
A34: THE ARGUMENT: same total revenue as Scenario 1, redistributed. Low users (27% of district) get +5-19% instead of +89-96%. Heavy users (top 3%) pay MORE than S1. Marginal price above 20k = $6-8 + $4.90 NFBWA = $10.90-12.90/kGal - a real conservation signal (S1: ~$8).
A36: PUSHBACK ON EVO: (1) No scenario models the tax lever - each +$0.01/100 raises ~$45.7k/yr on the $466.7M base; freezing $0.128 is a distributional CHOICE, not arithmetic. (2) Sewer $55 "designed to cover Garbage & Recycling" (their p.4) - a garbage bill hidden in a sewer line. (3) S2's $100/connection fee is a poll tax: car wash and widow pay the same. (4) Legal fees ran 196% of budget; $150k pre-budgeted to fight ratepayers at the PUC; $187k Jason's Deli reimbursement in capital outlay. (5) "Eliminated" constable/streetlight/irrigation costs shift to the HOA - total household cost is bill + dues.
A38: HONEST WEAKNESSES OF S3: (a) O&M tax cap set by voter authorization at district creation - VERIFY headroom before proposing (one TPIA line); if capped, the tax slice moves back onto middle tiers. (b) Steep-tier revenue is elastic - if heavy users conserve, revenue undershoots; partial offset: each conserved kGal saves the district $4.90 NFBWA + GL4 purchase costs; an S3 rate order needs an annual true-up clause. (c) Renters reach the tax only via landlords. (d) Tax deductibility helps itemizers only.
A40: S1 40-50k water tier not printed in handout; $4.50 assumed. Commercial modeled as the 9 accounts on handout p.2; uplift lever in B15 (+25% default - EVO itself admits S1 commercial is below Houston/Fulshear parity).

Sheet COS Extrapolation
A1: Cost-of-Service Extrapolation from the FY2027 Proposed Budget
A2: EVO produced a financial plan, not a COS study. This sheet functionalizes the district budget into water / sewer / garbage direct costs and prices a COS-pure bill. Blue cells are inputs/levers.
A4: 1. REVENUE REQUIREMENT CLOSURE (FY27 proposed budget)
A5: Total operating expenditures | B5: 3209500
A6: Total capital outlay | B6: 525814
A7: less: Maintenance tax collections | B7: -596600
A8: less: Sales tax revenue | B8: -350000
A9: less: Interest income | B9: -183100
A10: less: NFBWA pass-through revenue | B10: -700008
A11: less: Grease/transfer/penalty/misc revenues | B11: -20600
A12: less: Transfer from SPA reserves | B12: -934083
A13: Required from service rates (sum of the above) | B13: =SUM(B5:B12) -> 950923 | C13: EVO S1 target: $950,922 - closes to within $1
A15: 2. DIRECT COSTS BY FUNCTION (FY27 budget lines)
A16: Function | B16: Line items included | C16: Annual $
A17: Water | B17: Billing 3,700 + Operations 31,300 + M&R 78,500 + Lab 9,900 + Transfer 1,800 + Permits 1,800 + TCEQ 2,377 + Purchased water GL4 129,600 + Smart meters 8,800 + Irrigation evals 400 | C17: 268177
A18: Sewer | B18: Billing 3,700 + Operations 8,100 + Grease insp 8,600 + M&R 109,200 + Mowing 3,200 + Lift station 5,500 + Phone 3,600 + TCEQ 2,377 + Purchased sewer GL4 246,919 | C18: 391196
A19: Garbage & recycling | B19: Garbage expense | C19: 301400
A20: Sum of direct costs | C20: =SUM(C17:C19) -> 960773 | D20: =C20/B13 -> 1.0103584 | E20: of the rate target -> rates recover W+S+garbage at ~cost; admin/security/streetlights/capital/RWDS ride on taxes+interest+SPA drawdown
A22: 3. SYSTEM UNITS & ALLOCATION LEVERS
A23: System water sold, kGal/yr (679 res @ bracket model + 9 comm accts) | B23: 130600
A24: Total connections (679 residential + 9 commercial) | B24: 688
A25: Sewer allocation weight: 0 = all per-connection, 1 = all per-flow | B25: 0.5
A26: Water direct cost, $/kGal | B26: =C17/$B$23 -> 2.0534227
A27: Sewer: per-connection $/mo | per-flow $/kGal | B27: =C18/$B$24/12 -> 47.383236 | C27: =C18/$B$23 -> 2.9953752
A28: Garbage, $/connection/mo | B28: =C19/$B$24/12 -> 36.506783
A29: True marginal cost of water = water direct + NFBWA $4.90 | B29: =$B$26+4.9 -> 6.9534227 | C29: per 1,000 gal - compare S1 tier prices of $1.00-$3.00: marginal water priced BELOW cost, recovered in fixed charges instead
A31: 4. COS-PURE MONTHLY BILL vs EVO S1 (water+sewer+garbage, excl NFBWA which is identical everywhere)
A32: Usage kGal | B32: COS-pure bill | C32: S1 bill | D32: COS vs S1 | E32: Note
A33: 4 | B33: =$B$26*$A33+(1-$B$25)*$B$27+$B$25*$C$27*$A33+$B$28 -> 74.402842 | C33: =30+1.5*MAX(0,MIN($A33,10)-5)+2*MAX(0,MIN($A33,15)-10)+2.5*MAX(0,MIN($A33,20)-15)+3*MAX(0,MIN($A33,25)-20)+3.5*MAX(0,MIN($A33,30)-25)+4*MAX(0,MIN($A33,35)-30)+4.5*MAX(0,MIN($A33,50)-35)+5*MAX(0,$A33-50)+IF($A33<=20,55,IF($A33<=30,60,IF($A33<=40,65,IF($A33<=50,70,75)))) -> 85 | D33: =B33-C33 -> -10.597158
A34: 7 | B34: =$B$26*$A34+(1-$B$25)*$B$27+$B$25*$C$27*$A34+$B$28 -> 85.056173 | C34: =30+1.5*MAX(0,MIN($A34,10)-5)+2*MAX(0,MIN($A34,15)-10)+2.5*MAX(0,MIN($A34,20)-15)+3*MAX(0,MIN($A34,25)-20)+3.5*MAX(0,MIN($A34,30)-25)+4*MAX(0,MIN($A34,35)-30)+4.5*MAX(0,MIN($A34,50)-35)+5*MAX(0,$A34-50)+IF($A34<=20,55,IF($A34<=30,60,IF($A34<=40,65,IF($A34<=50,70,75)))) -> 88 | D34: =B34-C34 -> -2.943827 | E34: neighbor at 3918
A35: 8 | B35: =$B$26*$A35+(1-$B$25)*$B$27+$B$25*$C$27*$A35+$B$28 -> 88.607283 | C35: =30+1.5*MAX(0,MIN($A35,10)-5)+2*MAX(0,MIN($A35,15)-10)+2.5*MAX(0,MIN($A35,20)-15)+3*MAX(0,MIN($A35,25)-20)+3.5*MAX(0,MIN($A35,30)-25)+4*MAX(0,MIN($A35,35)-30)+4.5*MAX(0,MIN($A35,50)-35)+5*MAX(0,$A35-50)+IF($A35<=20,55,IF($A35<=30,60,IF($A35<=40,65,IF($A35<=50,70,75)))) -> 89.5 | D35: =B35-C35 -> -0.89271675 | E35: your normal month
A36: 12.5 | B36: =$B$26*$A36+(1-$B$25)*$B$27+$B$25*$C$27*$A36+$B$28 -> 104.58728 | C36: =30+1.5*MAX(0,MIN($A36,10)-5)+2*MAX(0,MIN($A36,15)-10)+2.5*MAX(0,MIN($A36,20)-15)+3*MAX(0,MIN($A36,25)-20)+3.5*MAX(0,MIN($A36,30)-25)+4*MAX(0,MIN($A36,35)-30)+4.5*MAX(0,MIN($A36,50)-35)+5*MAX(0,$A36-50)+IF($A36<=20,55,IF($A36<=30,60,IF($A36<=40,65,IF($A36<=50,70,75)))) -> 97.5 | D36: =B36-C36 -> 7.0872794 | E36: district median
A37: 17.5 | B37: =$B$26*$A37+(1-$B$25)*$B$27+$B$25*$C$27*$A37+$B$28 -> 122.34283 | C37: =30+1.5*MAX(0,MIN($A37,10)-5)+2*MAX(0,MIN($A37,15)-10)+2.5*MAX(0,MIN($A37,20)-15)+3*MAX(0,MIN($A37,25)-20)+3.5*MAX(0,MIN($A37,30)-25)+4*MAX(0,MIN($A37,35)-30)+4.5*MAX(0,MIN($A37,50)-35)+5*MAX(0,$A37-50)+IF($A37<=20,55,IF($A37<=30,60,IF($A37<=40,65,IF($A37<=50,70,75)))) -> 108.75 | D37: =B37-C37 -> 13.592831
A38: 22.5 | B38: =$B$26*$A38+(1-$B$25)*$B$27+$B$25*$C$27*$A38+$B$28 -> 140.09838 | C38: =30+1.5*MAX(0,MIN($A38,10)-5)+2*MAX(0,MIN($A38,15)-10)+2.5*MAX(0,MIN($A38,20)-15)+3*MAX(0,MIN($A38,25)-20)+3.5*MAX(0,MIN($A38,30)-25)+4*MAX(0,MIN($A38,35)-30)+4.5*MAX(0,MIN($A38,50)-35)+5*MAX(0,$A38-50)+IF($A38<=20,55,IF($A38<=30,60,IF($A38<=40,65,IF($A38<=50,70,75)))) -> 127.5 | D38: =B38-C38 -> 12.598382
A39: 24 | B39: =$B$26*$A39+(1-$B$25)*$B$27+$B$25*$C$27*$A39+$B$28 -> 145.42505 | C39: =30+1.5*MAX(0,MIN($A39,10)-5)+2*MAX(0,MIN($A39,15)-10)+2.5*MAX(0,MIN($A39,20)-15)+3*MAX(0,MIN($A39,25)-20)+3.5*MAX(0,MIN($A39,30)-25)+4*MAX(0,MIN($A39,35)-30)+4.5*MAX(0,MIN($A39,50)-35)+5*MAX(0,$A39-50)+IF($A39<=20,55,IF($A39<=30,60,IF($A39<=40,65,IF($A39<=50,70,75)))) -> 132 | D39: =B39-C39 -> 13.425047 | E39: your July 2026
A40: 35 | B40: =$B$26*$A40+(1-$B$25)*$B$27+$B$25*$C$27*$A40+$B$28 -> 184.48726 | C40: =30+1.5*MAX(0,MIN($A40,10)-5)+2*MAX(0,MIN($A40,15)-10)+2.5*MAX(0,MIN($A40,20)-15)+3*MAX(0,MIN($A40,25)-20)+3.5*MAX(0,MIN($A40,30)-25)+4*MAX(0,MIN($A40,35)-30)+4.5*MAX(0,MIN($A40,50)-35)+5*MAX(0,$A40-50)+IF($A40<=20,55,IF($A40<=30,60,IF($A40<=40,65,IF($A40<=50,70,75)))) -> 177.5 | D40: =B40-C40 -> 6.9872603
A42: READ: with the allocation weight at 0.5 (half connection-based, half flow-based sewer), a COS-pure bill tracks S1 closely for mid users but charges low users materially less and heavy users more. Set the weight to 0 and S1 looks generous to heavy users; set it to 1 and S1 overcharges every low user. THE ALLOCATION CHOICE IS THE WHOLE RATE DEBATE, and EVO never made it openly.
A44: THE THREE COS-GROUNDED ASKS: (1) commission a real AWWA M1 cost-of-service study with class demand data before adopting any rate order; (2) adopt winter-averaged volumetric sewer (bill sewer on Dec-Feb usage - the industry-standard compromise); (3) put garbage (~$37/connection/mo, a third of the proposed $55 "sewer" charge) on its own labeled bill line.
A46: CAVEATS: direct-cost split leaves admin/bookkeeping/engineering in the tax-funded bucket; shifting a share into W/S raises the "at cost" figure ~10-20%. RWDS reclaimed-water costs ($420k: NFBWA RWDS $232,206 + GL4 RWDS $187,972) excluded - arguably an irrigation subsidy benefiting heavy irrigators. System kGal/yr estimated from the bracket model; a real COS would use actual production and billing records.

Sheet Anomalies & Money Owed
A1: Anomalies, Fees and Money Potentially Recoverable
A3: # | B3: Date | C3: Finding | D3: Amount $ | E3: Severity | F3: How to prove it / what to ask for
A4: 1 | B4: 2021-08 | C4: $150.00 DEPOSIT paid at account opening. It appears on the first bill and never again - no refund, no credit, no application to a balance in the 59 bills since. | D4: 150 | E4: HIGH | F4: RESEARCHED - Rate Order Sec. 3.01: deposit is held until FINAL termination of service, then credited against any balance and the remainder refunded within 60 days, no interest. No early-refund clause. Action: get written confirmation from MDS that the $150 is recorded on the account so it is not lost at move-out.
A5: 2 | B5: 2021-08 | C5: $30.00 TRANSFER FEE on the opening bill. | D5: 30 | E5: LOW | F5: One-time, legitimate. Listed for completeness.
A6: 3 | B6: 2021-12 | C6: $7.50 late penalty charged, then REVERSED the next month as "FEE REMOVED -7.50". | D6: 0 | E6: PRECEDENT | F6: This is the most useful line in the whole file. The district has already demonstrated it will reverse a penalty on this account. Cite it when asking for the others back.
A7: 4 | B7: 2023-03 | C7: $1.68 late penalty. Auto-pay did not capture the Feb 2023 bill. | D7: 1.68 | E7: MED | F7: Bill shows BALANCE FORWARD 18.48 = 16.80 + 1.68. No PAYMENT line that cycle.
A8: 5 | B8: 2024-06 | C8: $8.91 late penalty. Auto-pay failed on the May 2024 bill. | D8: 8.91 | E8: MED | F8: Reconstructed from the Jul 2024 balance-forward of $187.11 = 89.10 + 89.10 + 8.91.
A9: 6 | B9: 2024-07 | C9: $10.00 DELINQUENT LTR fee - a charge for mailing a letter about a payment the auto-pay was supposed to make. | D9: 10 | E9: HIGH | F9: Rate Order Sec. 4.01 authorizes $10 per written delinquency notice, so it was not a billing error. Request goodwill reversal citing the Dec-2021 FEE REMOVED precedent.
A10: 7 | B10: 2025-02 | C10: $7.93 late penalty. Auto-pay failed on the Jan 2025 bill. | D10: 7.93 | E10: MED | F10: Feb 2025 bill shows BALANCE FORWARD 87.23 = 79.30 + 7.93, and no PAYMENT line.
A11: 8 | B11: 2025-03 | C11: $10.00 DELINQUENT LTR fee. | D11: 10 | E11: HIGH | F11: Second occurrence. Same argument.
A12: 9 | B12: 2025-06 | C12: $9.40 late penalty. Auto-pay failed on the May 2025 bill. | D12: 9.4 | E12: MED | F12: Jun 2025 bill shows BALANCE FORWARD 103.40 = 94.00 + 9.40.
A13: 10 | B13: 2026-07 | C13: CLUE + CAUTION. The Jul 2026 bill prints: "Your credit Card Account will be expired next month. Please call in your new card Don't pay this bill." Mundane reading: auto-pay card expiring, draft will handle the bill. Cautious reading: "call in your card" is classic utility-scam wording. Note the auto-pay failure gaps (15/8/4 months) do NOT match a card-expiry cycle. | D13: 0 | E13: ACTION | F13: Do NOT act on the message as printed. Re-read the physical bill, then verify and update the card ONLY via the number on your older bills (281-290-6500) or by logging into mdswater.com directly. Set a calendar reminder for every card expiry.
A14: 11 | B14: 2024-06 | C14: The June 2024 bill is MISSING from your records entirely. | D14: 0 | E14: MED | F14: Meter reads bracket it (1055 -> 1064 = 9,000 gal) and the balance chain reconciles, so nothing is hidden - but request a duplicate from MDS for a complete file.
A15: 12 | B15: 2023-08 | C15: WATER charged $11.50 on 21,000 gallons where the $0.50/1,000 rate implies $10.50. Reveals an unpublished tier above 20,000 gallons. | D15: 1 | E15: LOW | F15: Immaterial in dollars, but ask for the adopted rate order. You should not have to solve algebra to learn your own tier schedule.
A16: 13 | B16: 2026-01 | C16: IRRIGATION OVERUSE (originally flagged as leak signature), onset mid-Dec 2025. Confirmed Aug 2026 via EyeOnWater: spikes on the Mon/Wed/Fri sprinkler schedule, no continuous flow. Winter shutdown skipped + per-run volume growing (~3,000+ gal/run, ~3x agronomic need, +45% WoW in Aug). | D16: 426.7 | E16: CRITICAL | F16: $426.70 excess Jan-Jul 2026 vs same months 2025 at identical rates; Aug pace implies a ~$350 bill if unchanged. Fix: reprogram controller (check stacked programs, run minutes, seasonal adjust; off Nov-Feb), inspect zones for a break, book free NFBWA W.I.S.E. Guys evaluation. If a physical fault is found, request discretionary Board relief with repair receipt.
C18: Recoverable: late fees + delinquent letter fees | D18: =D7+D8+D9+D10+D11+D12 -> 47.92
C19: Recoverable: unrefunded deposit | D19: =D4 -> 150
C20: Excess billing from the 2026 leak, Jan-Jul | D20: =D16 -> 426.7
C21: TOTAL AT STAKE | D21: =D18+D19+D20 -> 624.62

Sheet Irrigation Evidence
A1: Statistical Case: Irrigation Overuse Starting Mid-December 2025 (confirmed via EyeOnWater smart-meter data, Aug 2026)
A3: Test 1: Is 2026 usage an outlier against the 2021-2025 record?
A4: Month | B4: kGal | C4: Baseline Mean | D4: Baseline SD | E4: Z-score | F4: Verdict
A5: 2026-01-13 | B5: 15 | C5: =AVERAGE('Bill Ledger'!$F$5:$F$57) -> 9.5471698 | D5: =STDEV('Bill Ledger'!$F$5:$F$57) -> 4.8101097 | E5: =(B5-C5)/D5 -> 1.1336187 | F5: =IF(E5>2,"OUTLIER (>2 SD)",IF(E5>1,"elevated","within range")) -> elevated
A6: 2026-02-13 | B6: 11 | C6: =AVERAGE('Bill Ledger'!$F$5:$F$57) -> 9.5471698 | D6: =STDEV('Bill Ledger'!$F$5:$F$57) -> 4.8101097 | E6: =(B6-C6)/D6 -> 0.30203681 | F6: =IF(E6>2,"OUTLIER (>2 SD)",IF(E6>1,"elevated","within range")) -> within range
A7: 2026-03-13 | B7: 15 | C7: =AVERAGE('Bill Ledger'!$F$5:$F$57) -> 9.5471698 | D7: =STDEV('Bill Ledger'!$F$5:$F$57) -> 4.8101097 | E7: =(B7-C7)/D7 -> 1.1336187 | F7: =IF(E7>2,"OUTLIER (>2 SD)",IF(E7>1,"elevated","within range")) -> elevated
A8: 2026-04-13 | B8: 22 | C8: =AVERAGE('Bill Ledger'!$F$5:$F$57) -> 9.5471698 | D8: =STDEV('Bill Ledger'!$F$5:$F$57) -> 4.8101097 | E8: =(B8-C8)/D8 -> 2.5888869 | F8: =IF(E8>2,"OUTLIER (>2 SD)",IF(E8>1,"elevated","within range")) -> OUTLIER (>2 SD)
A9: 2026-05-13 | B9: 22 | C9: =AVERAGE('Bill Ledger'!$F$5:$F$57) -> 9.5471698 | D9: =STDEV('Bill Ledger'!$F$5:$F$57) -> 4.8101097 | E9: =(B9-C9)/D9 -> 2.5888869 | F9: =IF(E9>2,"OUTLIER (>2 SD)",IF(E9>1,"elevated","within range")) -> OUTLIER (>2 SD)
A10: 2026-06-13 | B10: 25 | C10: =AVERAGE('Bill Ledger'!$F$5:$F$57) -> 9.5471698 | D10: =STDEV('Bill Ledger'!$F$5:$F$57) -> 4.8101097 | E10: =(B10-C10)/D10 -> 3.2125733 | F10: =IF(E10>2,"OUTLIER (>2 SD)",IF(E10>1,"elevated","within range")) -> OUTLIER (>2 SD)
A11: 2026-07-13 | B11: 24 | C11: =AVERAGE('Bill Ledger'!$F$5:$F$57) -> 9.5471698 | D11: =STDEV('Bill Ledger'!$F$5:$F$57) -> 4.8101097 | E11: =(B11-C11)/D11 -> 3.0046779 | F11: =IF(E11>2,"OUTLIER (>2 SD)",IF(E11>1,"elevated","within range")) -> OUTLIER (>2 SD)
A12: 2026 mean | B12: =AVERAGE(B5:B11) -> 19.142857 | E12: =(B12-C5)/(D5/SQRT(7)) -> 5.278009 | F12: Z of the MEAN = +5.3 - illustrative only: monthly usage is seasonal and autocorrelated, so the independence assumption is violated. The decisive test is Test 2 rows below and the winter comparison: all 12 prior winter months were 2-8 kGal; all three 2026 winter months are 11-15 kGal. Zero overlap.
A15: Test 2: The floor, not the peak, is what moved
A16: A behaviour change (bigger lawn, more guests, hotter summer) raises your PEAK months. A leak raises your FLOOR - the lowest month of the year - because it never stops running.
A17: Year | B17: Lowest Month kGal | C17: Highest Month kGal | D17: Spread
A18: 2021 | B18: =MIN('Bill Ledger'!$F$5:$F$9) -> 3 | C18: =MAX('Bill Ledger'!$F$5:$F$9) -> 14 | D18: =C18-B18 -> 11
A19: 2022 | B19: =MIN('Bill Ledger'!$F$10:$F$21) -> 3 | C19: =MAX('Bill Ledger'!$F$10:$F$21) -> 18 | D19: =C19-B19 -> 15
A20: 2023 | B20: =MIN('Bill Ledger'!$F$22:$F$33) -> 2 | C20: =MAX('Bill Ledger'!$F$22:$F$33) -> 21 | D20: =C20-B20 -> 19
A21: 2024 | B21: =MIN('Bill Ledger'!$F$34:$F$45) -> 3 | C21: =MAX('Bill Ledger'!$F$34:$F$45) -> 15 | D21: =C21-B21 -> 12
A22: 2025 | B22: =MIN('Bill Ledger'!$F$46:$F$57) -> 3 | C22: =MAX('Bill Ledger'!$F$46:$F$57) -> 18 | D22: =C22-B22 -> 15
A23: 2026 | B23: =MIN('Bill Ledger'!$F$58:$F$64) -> 11 | C23: =MAX('Bill Ledger'!$F$58:$F$64) -> 25 | D23: =C23-B23 -> 14
A25: The floor sat at 2-3 kGal every year 2021-2025. In 2026 it is 11 kGal. Cause confirmed: the irrigation winter shutdown was skipped starting mid-Dec 2025.
A28: Test 3: How big is the leak, in plumbing terms?
A29: Excess gallons, Jan-Jul 2026 vs Jan-Jul 2025 | B29: =SUMIFS('Bill Ledger'!$F$5:$F$64,'Bill Ledger'!$B$5:$B$64,2026)-SUMIFS('Bill Ledger'!$F$5:$F$64,'Bill Ledger'!$B$5:$B$64,2025,'Bill Ledger'!$C$5:$C$64,"<=7") -> 73
A30: Days in that window (Dec 13 to Jul 13) | B30: 212
A31: Excess flow, gallons per day | B31: =B29*1000/B30 -> 344.33962
A32: Excess flow, gallons per minute | B32: =B31/1440 -> 0.23912474
A33: Excess flow, drips per minute equivalent | B33: =B32*3785/0.05 -> 18101.743
A35: CONFIRMED Aug 2026 via EyeOnWater: usage spikes land on the Mon/Wed/Fri irrigation schedule; no continuous-flow leak detected. ~3,000+ gallons per run at current pace (11,606 gal/week, +45% WoW).
A36: Two changes: (1) irrigation ran through winter for the first time on record; (2) per-run volume grew and is still growing - consistent with over-programming (stacked programs, long run times) or a pressurized-only fault (cracked lateral, broken head, weeping valve).
A38: Fix: check controller (run minutes, seasonal adjust, stacked programs A/B/C); compare per-run gallons in EyeOnWater Hour view (this week vs May vs last Oct); walk zones during a run.
A39: Book the free NFBWA W.I.S.E. Guys irrigation evaluation (nfbwa.com/wise-guys). Target: ~1 inch/week (~3,000 gal/WEEK) in summer, near zero Nov-Feb. Current use is ~3x that.
